tool4NC/__init__.py
tool4NC-0.0.5.dist-info/LICENSE
tool4NC-0.0.5.dist-info/METADATA
tool4NC-0.0.5.dist-info/WHEEL
tool4NC-0.0.5.dist-info/top_level.txt
tool4NC-0.0.5.dist-info/RECORD
